testy/__init__.py
testy/async_support.py
testy/cli.py
testy/core.py
testy/lifecycle.py
testy/parameterized.py
Testy_jest_like_python_testing_framework-0.1.0.dist-info/METADATA
Testy_jest_like_python_testing_framework-0.1.0.dist-info/WHEEL
Testy_jest_like_python_testing_framework-0.1.0.dist-info/entry_points.txt
Testy_jest_like_python_testing_framework-0.1.0.dist-info/top_level.txt
Testy_jest_like_python_testing_framework-0.1.0.dist-info/RECORD
