Metadata-Version: 2.1
Name: Testy---jest-like-python-testing-framework
Version: 0.1.0
Summary: A Jest-like Python testing framework
Home-page: https://github.com/GaoFan98/testy
Author: Vagif Aghayev
Author-email: vagifaghayev270298@gmail.com
Classifier: Programming Language :: Python :: 3
Classifier: License :: OSI Approved :: MIT License
Classifier: Operating System :: OS Independent
Requires-Python: >=3.6
